{
  "company": "Brex",
  "role_title": "Staff Product Manager, Growth",
  "url": "https://www.brex.com/careers/8436530002?gh_jid=8436530002",
  "ats_provider": "greenhouse",
  "ats_job_id": "8436530002",
  "fetched_at": "2026-05-10",
  "posting_first_seen": null,
  "posting_last_updated": null,
  "location": {
    "type": "hybrid",
    "cities_listed": [
      "San Francisco, CA",
      "Seattle, WA",
      "New York City, NY"
    ],
    "remote_us_eligible": false,
    "office_time_required": "at least 3 days per week on Monday, Wednesday and Thursday",
    "work_auth": "open",
    "visa_sponsorship": "unclear"
  },
  "archetype": "Growth PM",
  "archetype_confidence": "high",
  "secondary_archetype": "Technical PM (GTM systems / AI-powered infrastructure)",
  "seniority": {
    "level": "Staff PM (IC6 equivalent)",
    "years_required_min": null,
    "years_required_max": null,
    "manages_people": false,
    "level_signals": [
      "Role titled 'Staff Product Manager'",
      "Comp range $240K–$300K base, consistent with Staff IC at a late-stage fintech",
      "Expected to own company-level metrics and influence executives",
      "Expected to 'Help define and scale Brex's Growth Product function'"
    ]
  },
  "must_haves": [
    {
      "id": "gtm_systems_experience",
      "raw_text_from_jd": "Experience building and scaling growth, revenue, or GTM systems in a high-growth technology company.",
      "skill_type": "domain_knowledge",
      "domain": "GTM_systems",
      "evidence_required": "work_history",
      "bridgeable": "no",
      "severity": "hard",
      "tools_named": [],
      "technologies_named": [],
      "industries_named": [],
      "geographies_named": [],
      "employer_types_named": [
        "high-growth technology company"
      ],
      "credentials_named": []
    },
    {
      "id": "company_level_metrics_ownership",
      "raw_text_from_jd": "Experience owning and materially moving company-level metrics.",
      "skill_type": "outcome",
      "domain": "growth_metrics",
      "evidence_required": "shipped_products_with_metrics",
      "bridgeable": "no",
      "severity": "hard",
      "tools_named": [],
      "technologies_named": [],
      "industries_named": [],
      "geographies_named": [],
      "employer_types_named": [],
      "credentials_named": []
    },
    {
      "id": "systems_thinking",
      "raw_text_from_jd": "Strong systems thinking — ability to identify leverage points across product, process, and people systems.",
      "skill_type": "capability",
      "domain": "systems_design",
      "evidence_required": "project_examples",
      "bridgeable": "maybe",
      "severity": "hard",
      "tools_named": [],
      "technologies_named": [],
      "industries_named": [],
      "geographies_named": [],
      "employer_types_named": [],
      "credentials_named": []
    },
    {
      "id": "cross_functional_leadership",
      "raw_text_from_jd": "Demonstrated track record of leading complex, cross-functional initiatives with executive visibility.",
      "skill_type": "capability",
      "domain": "cross_functional_leadership",
      "evidence_required": "work_history",
      "bridgeable": "maybe",
      "severity": "hard",
      "tools_named": [],
      "technologies_named": [],
      "industries_named": [],
      "geographies_named": [],
      "employer_types_named": [],
      "credentials_named": []
    },
    {
      "id": "analytical_fluency",
      "raw_text_from_jd": "Deep analytical fluency; comfortable working with funnel metrics, experimentation frameworks, and data tools (SQL proficiency preferred).",
      "skill_type": "capability",
      "domain": "data_analytics",
      "evidence_required": "work_history",
      "bridgeable": "maybe",
      "severity": "hard",
      "tools_named": [],
      "technologies_named": [
        "SQL"
      ],
      "industries_named": [],
      "geographies_named": [],
      "employer_types_named": [],
      "credentials_named": []
    },
    {
      "id": "high_ownership_ambiguity",
      "raw_text_from_jd": "High ownership mindset with the ability to operate in ambiguity and build from first principles.",
      "skill_type": "cultural_fit",
      "domain": "team_culture",
      "evidence_required": "project_examples",
      "bridgeable": "yes",
      "severity": "hard",
      "tools_named": [],
      "technologies_named": [],
      "industries_named": [],
      "geographies_named": [],
      "employer_types_named": [],
      "credentials_named": []
    }
  ],
  "nice_to_haves": [
    {
      "id": "sql_proficiency",
      "raw_text_from_jd": "Deep analytical fluency; comfortable working with funnel metrics, experimentation frameworks, and data tools (SQL proficiency preferred).",
      "skill_type": "tool_proficiency",
      "domain": "data_querying",
      "evidence_required": "hands_on_use",
      "bridgeable": "yes",
      "severity": "soft",
      "tools_named": [],
      "technologies_named": [
        "SQL"
      ],
      "industries_named": [],
      "geographies_named": [],
      "employer_types_named": [],
      "credentials_named": []
    }
  ],
  "explicitly_excluded": [],
  "scope": {
    "team_size_estimate": "unclear",
    "surface": "GTM growth infrastructure — AI agents, outbound/lifecycle automation, pipeline scoring, onboarding optimization, experimentation frameworks, revenue tooling",
    "business_model": "B2B SaaS / fintech — corporate cards, spend management, banking",
    "primary_metrics_inferred": [
      "Pipeline dollars",
      "Conversion rates",
      "Customer activation",
      "Retention",
      "Revenue"
    ],
    "cross_functional_partners": [
      "Sales",
      "Marketing",
      "RevOps",
      "Engineering",
      "Legal",
      "IT",
      "Data",
      "Design"
    ],
    "core_responsibilities": [
      "Own a critical GTM-related metric and define the product strategy and roadmap to drive step-change improvements.",
      "Identify structural bottlenecks across the revenue funnel — spanning tooling, automation, data, incentives, and workflows — and design systems to address them.",
      "Lead 0→1 and 1→N initiatives that re-architect Brex's GTM infrastructure.",
      "Partner deeply with Sales, Marketing, RevOps, Engineering, Legal, IT, and Data to drive high-impact outcomes.",
      "Influence stakeholders and executives through clear strategy, strong business cases, and measurable results.",
      "Establish clear input and output metrics, and operate with rigor on experimentation, prioritization, and tradeoffs.",
      "Help define and scale Brex's Growth Product function as it evolves."
    ]
  },
  "compensation": {
    "base_range_usd": [
      240000,
      300000
    ],
    "total_comp_estimate_usd": null,
    "equity_mentioned": true,
    "equity_form": "equity and other forms of compensation may be provided as part of a total compensation package",
    "location_pay_differential": true,
    "source": "stated"
  },
  "top_keywords": [
    "GTM systems",
    "AI agents",
    "revenue growth",
    "growth infrastructure",
    "experimentation frameworks",
    "pipeline prioritization",
    "lifecycle automation",
    "funnel optimization",
    "staff PM",
    "outbound automation",
    "ML-driven models",
    "RevOps"
  ],
  "buzzword_density": "high",
  "green_flags": [
    "Compensation range disclosed and competitive ($240K–$300K base)",
    "Clear product surface and ownership area with specific initiative examples",
    "Dedicated engineering and design team",
    "Explicit metric ownership — company-level GTM metrics",
    "Role has strategic scope: 'Help define and scale Brex's Growth Product function'"
  ],
  "red_flags": [
    "Hybrid policy requires 3 specific days in office (Mon/Wed/Thu) in SF, Seattle, or NYC — eliminates remote candidates",
    "Remote allowance limited to 4 weeks per year (minimum 1 week at a time)",
    "SQL listed as 'preferred' in requirements section but the requirement also says 'deep analytical fluency' as a hard requirement — SQL itself is ambiguous hard vs. soft",
    "High buzzword density (AI agents, autonomous agents, ML-driven models) may obscure actual scope",
    "No years-of-experience floor stated, making calibration unclear",
    "Visa sponsorship status not addressed"
  ],
  "extraction_notes": {
    "fields_inferred_not_stated": [
      "seniority.level (inferred from title 'Staff' + comp range)",
      "scope.business_model (inferred from company description)",
      "scope.primary_metrics_inferred (inferred from 'What you'll do' section, not a direct responsibility list)",
      "location.work_auth (not stated; defaulted to 'open')",
      "location.visa_sponsorship (not stated; defaulted to 'unclear')",
      "compensation.location_pay_differential (inferred from 'starting base pay will depend on a number of factors including the candidate's location')"
    ],
    "ambiguities": [
      "SQL proficiency appears in the Requirements (must-haves) section with the qualifier 'preferred' — captured as both a hard requirement (analytical fluency) and a soft nice-to-have (SQL specifically).",
      "No explicit years-of-experience minimum stated anywhere in the JD; seniority inferred from title and comp range only."
    ]
  }
}